[{"Name":"电锅炖鸡汤","ImageUrl":"http://site.meishij.net/r/23/159/2414773/a2414773_23218.jpg","DetailUrl":"http://www.meishij.net/zuofa/dianguodunjitang_1.html","DetailID":"yunfu/detail/dianguodunjitang_1.json","CategoryName":"孕妇","CategoryReName":"yunfu"},{"Name":"猕猴桃奶昔","ImageUrl":"http://site.meishij.net/r/208/36/1259208/a1259208_30491.jpg","DetailUrl":"http://www.meishij.net/zuofa/houtaonaixi_1.html","DetailID":"yunfu/detail/houtaonaixi_1.json","CategoryName":"孕妇","CategoryReName":"yunfu"},{"Name":"凉拌苦瓜","ImageUrl":"http://site.meishij.net/r/208/36/1259208/a1259208_57667.jpg","DetailUrl":"http://www.meishij.net/chufang/diy/langcaipu/5538.html","DetailID":"yunfu/detail/5538.json","CategoryName":"孕妇","CategoryReName":"yunfu"},{"Name":"牛奶蒸鸡蛋 ","ImageUrl":"http://site.meishij.net/r/239/198/2299739/a2299739_57107.jpg","DetailUrl":"http://www.meishij.net/zuofa/niunaizhengjidan.html","DetailID":"yunfu/detail/niunaizhengjidan.json","CategoryName":"孕妇","CategoryReName":"yunfu"},{"Name":"黄瓜银耳汤","ImageUrl":"http://site.meishij.net/r/117/242/1123117/a1123117_49973.jpg","DetailUrl":"http://www.meishij.net/zuofa/huangguayinertang_5.html","DetailID":"yunfu/detail/huangguayinertang_5.json","CategoryName":"孕妇","CategoryReName":"yunfu"},{"Name":"香菇豆腐鲫鱼汤","ImageUrl":"http://site.meishij.net/r/117/242/1123117/a1123117_04537.jpg","DetailUrl":"http://www.meishij.net/zuofa/xianggudoufujiyutang.html","DetailID":"yunfu/detail/xianggudoufujiyutang.json","CategoryName":"孕妇","CategoryReName":"yunfu"},{"Name":"蒜香炒肝尖","ImageUrl":"http://site.meishij.net/r/208/36/1259208/a1259208_34645.jpg","DetailUrl":"http://www.meishij.net/zuofa/suanxiangchaoganjian.html","DetailID":"yunfu/detail/suanxiangchaoganjian.json","CategoryName":"孕妇","CategoryReName":"yunfu"},{"Name":"蒸鸡蛋羹","ImageUrl":"http://site.meishij.net/r/202/30/2945202/a2945202_99348.jpg","DetailUrl":"http://www.meishij.net/zuofa/zhengjidangeng_3.html","DetailID":"yunfu/detail/zhengjidangeng_3.json","CategoryName":"孕妇","CategoryReName":"yunfu"},{"Name":"豆腐鲫鱼汤","ImageUrl":"http://site.meishij.net/r/185/123/1655935/a1655935_12161.jpg","DetailUrl":"http://www.meishij.net/zuofa/doufujiyutang_1.html","DetailID":"yunfu/detail/doufujiyutang_1.json","CategoryName":"孕妇","CategoryReName":"yunfu"},{"Name":"大枣红薯米饭","ImageUrl":"http://site.meishij.net/r/41/203/113291/a113291_07100.jpg","DetailUrl":"http://www.meishij.net/zuofa/dazaohongshumifan.html","DetailID":"yunfu/detail/dazaohongshumifan.json","CategoryName":"孕妇","CategoryReName":"yunfu"},{"Name":"鲫鱼蒸蛋","ImageUrl":"http://site.meishij.net/r/62/147/599312/a599312_81454.jpg","DetailUrl":"http://www.meishij.net/zuofa/jiyuzhengdan_11.html","DetailID":"yunfu/detail/jiyuzhengdan_11.json","CategoryName":"孕妇","CategoryReName":"yunfu"},{"Name":"香菇炖柴鸡","ImageUrl":"http://site.meishij.net/r/188/125/2281438/a2281438_22139.jpg","DetailUrl":"http://www.meishij.net/zuofa/xianggudunchaiji.html","DetailID":"yunfu/detail/xianggudunchaiji.json","CategoryName":"孕妇","CategoryReName":"yunfu"},{"Name":"莲藕棒骨汤","ImageUrl":"http://site.meishij.net/r/208/36/1259208/a1259208_28632.jpg","DetailUrl":"http://www.meishij.net/zuofa/lianoubanggutang_1.html","DetailID":"yunfu/detail/lianoubanggutang_1.json","CategoryName":"孕妇","CategoryReName":"yunfu"},{"Name":"陈皮绿豆鸽子汤","ImageUrl":"http://site.meishij.net/r/72/122/2343072/a2343072_99605.jpg","DetailUrl":"http://www.meishij.net/zuofa/chenpilvdougezitang.html","DetailID":"yunfu/detail/chenpilvdougezitang.json","CategoryName":"孕妇","CategoryReName":"yunfu"},{"Name":"酒酿鸡蛋汤","ImageUrl":"http://site.meishij.net/r/199/67/2891949/a2891949_10199.jpg","DetailUrl":"http://www.meishij.net/zuofa/jiuniangjidantang.html","DetailID":"yunfu/detail/jiuniangjidantang.json","CategoryName":"孕妇","CategoryReName":"yunfu"},{"Name":"豆腐鱼汤","ImageUrl":"http://site.meishij.net/r/112/161/977862/a977862_73182.jpg","DetailUrl":"http://www.meishij.net/zuofa/doufuyutang_2.html","DetailID":"yunfu/detail/doufuyutang_2.json","CategoryName":"孕妇","CategoryReName":"yunfu"},{"Name":"红枣鲫鱼木瓜汤","ImageUrl":"http://site.meishij.net/r/208/36/1259208/a1259208_29657.jpg","DetailUrl":"http://www.meishij.net/zuofa/hongzaojiyumuguatang.html","DetailID":"yunfu/detail/hongzaojiyumuguatang.json","CategoryName":"孕妇","CategoryReName":"yunfu"},{"Name":"冰糖雪梨","ImageUrl":"http://site.meishij.net/r/208/36/1259208/a1259208_92628.jpg","DetailUrl":"http://www.meishij.net/zuofa/zizhibingtangxueli.html","DetailID":"yunfu/detail/zizhibingtangxueli.json","CategoryName":"孕妇","CategoryReName":"yunfu"}]