{"Title":"白雪公主披萨饼的做法","Primary":["水90毫升","高筋面粉220克","草菇50克","马苏里拉奶酪200克","鸡蛋1只","紫甘蓝10克","圣女果100克","彩椒50克","玉米粒50克","虾仁100克"],"Auxiliary":["玉米淀粉适量","砂糖5克","盐3克","酵母粉2克","橄榄油13克","披萨酱100克","红曲粉适量","海苔适量"],"Flavoring":[],"Setups":["1.准备好食材","[image]:http://site.meishij.net/rs/08/28/69508/n69508_70034.jpg","2.将水、橄榄油、盐、砂糖都放入面包机中","[image]:http://site.meishij.net/rs/08/28/69508/n69508_90125.jpg","3.放入高筋面粉后在上面画个坑倒入酵母粉盖好","[image]:http://site.meishij.net/rs/08/28/69508/n69508_11132.jpg","4.选择面包机第10生面团选项，开启面包机","[image]:http://site.meishij.net/rs/08/28/69508/n69508_67336.jpg","5.将鸡蛋的蛋清和蛋黄分离打散后加入适量淀粉水，蛋清再分出两份一份加入少许紫甘蓝汁，一份加入少许红曲粉","[image]:http://site.meishij.net/rs/08/28/69508/n69508_01681.jpg","6.将蛋液分别摊成蛋饼备用","[image]:http://site.meishij.net/rs/08/28/69508/n69508_94525.jpg","7.面团发好后取出放砧板上揉匀排气","[image]:http://site.meishij.net/rs/08/28/69508/n69508_18436.jpg","8.披萨盘底刷一层橄榄油，将揉好的面团擀成圆片放入披萨盘中，外面一圈留向上卷起的边","[image]:http://site.meishij.net/rs/08/28/69508/n69508_09931.jpg","9.用叉子在面团上戳出一些洞帮助透气","[image]:http://site.meishij.net/rs/08/28/69508/n69508_96942.jpg","10.上面再刷一层橄榄油","[image]:http://site.meishij.net/rs/08/28/69508/n69508_25592.jpg","11.在面饼上放上切好的食材和一些奶酪","[image]:http://site.meishij.net/rs/08/28/69508/n69508_35662.jpg","12.上面用一层奶酪盖严，送入预热好的烤箱上下火200度烤15-20分钟","[image]:http://site.meishij.net/rs/08/28/69508/n69508_99799.jpg","13.将鸡蛋饼、小番茄、海苔刻出白雪公主","[image]:http://site.meishij.net/rs/08/28/69508/n69508_91330.jpg","14.披萨烤好后上面放上白雪公主，可以用一些番茄片装饰周围","[image]:http://site.meishij.net/rs/08/28/69508/n69508_95563.jpg","[image]:http://site.meishij.net/rs/19/208/1364519/n1364519_93734.jpg","[image]:http://site.meishij.net/rs/19/208/1364519/n1364519_63668.jpg","烹饪技巧","　　本来是按照面包机食谱上面披萨做的饼底，选择的是小的量，最后够我做两个8寸的披萨，所以这里我把原配方减掉了一半，就是一个8寸披萨的量。"]}