{"Title":"意式披萨酱的做法","Primary":["西红柿1个"],"Auxiliary":["洋葱100克"],"Flavoring":["食盐1小勺","蒜5瓣","番茄沙司100克","黑胡椒1小勺","罗勒1小勺","黄油30克","百里香1小勺"],"Setups":["1.准备、清洗食材；西红柿用开水烫一下或者在火上烤一下，去皮切成小丁，洋葱切小丁，大蒜切末；锅中放入黄油，小火融化后，倒入蒜末和洋葱丁，转中火翻炒到洋葱透明发软","[image]:http://images.meishij.net/p/20130222/a9b6a755fae2f86a1d48d6e15ff0df8f.jpg","2.倒入西红柿丁，转大火不断翻炒，到西红柿出沙；倒入100克番茄沙司炒匀；倒入1小勺干罗勒碎","[image]:http://images.meishij.net/p/20130222/f037d218e468593bd0073c906f147080.jpg","3.倒入1小勺干百里香碎；倒入一小勺黑胡椒碎，炒匀；转小火盖上盖子煮20分钟，出锅前加一小撮盐即可","[image]:http://images.meishij.net/p/20130222/cbe758c56cd7187999ee781ee3a4cc40.jpg","[image]:http://images.meishij.net/p/20130222/b2597176a033b5d1caccc766587189b6.jpg"]}