[{"Name":"豆角炒藕条","ImageUrl":"http://site.meishij.net/r/246/137/1534496/a1534496_142253162650667.jpg","DetailUrl":"http://www.meishij.net/zuofa/doujiaochaooutiao.html","DetailID":"wucan/detail/doujiaochaooutiao.json","CategoryName":"午餐","CategoryReName":"wucan"},{"Name":"糖醋带鱼","ImageUrl":"http://site.meishij.net/r/53/149/2912303/a2912303_142253121564984.jpg","DetailUrl":"http://www.meishij.net/zuofa/tangcudaiyu_30.html","DetailID":"wucan/detail/tangcudaiyu_30.json","CategoryName":"午餐","CategoryReName":"wucan"},{"Name":"炒瓜片鸡蛋","ImageUrl":"http://site.meishij.net/r/19/187/2609269/a2609269_142252833330914.jpg","DetailUrl":"http://www.meishij.net/zuofa/chaoguapianjidan.html","DetailID":"wucan/detail/chaoguapianjidan.json","CategoryName":"午餐","CategoryReName":"wucan"},{"Name":"肉末酱烧茄子","ImageUrl":"http://site.meishij.net/r/53/149/2912303/a2912303_142252753984546.jpg","DetailUrl":"http://www.meishij.net/zuofa/roumojiangshaoqiezi_3.html","DetailID":"wucan/detail/roumojiangshaoqiezi_3.json","CategoryName":"午餐","CategoryReName":"wucan"},{"Name":"酸豆角炒肉末","ImageUrl":"http://site.meishij.net/r/246/42/3260746/a3260746_142253747064671.jpg","DetailUrl":"http://www.meishij.net/zuofa/suandoujiaochaoroumo_16.html","DetailID":"wucan/detail/suandoujiaochaoroumo_16.json","CategoryName":"午餐","CategoryReName":"wucan"},{"Name":"枸杞叶瘦肉蛋花汤","ImageUrl":"http://site.meishij.net/r/17/180/732517/a732517_142258228643647.jpg","DetailUrl":"http://www.meishij.net/zuofa/gouqiyeshouroudanhuatang.html","DetailID":"wucan/detail/gouqiyeshouroudanhuatang.json","CategoryName":"午餐","CategoryReName":"wucan"},{"Name":"小笼包","ImageUrl":"http://site.meishij.net/r/17/180/732517/a732517_142257891147093.jpg","DetailUrl":"http://www.meishij.net/zuofa/xiaolongbao_6.html","DetailID":"wucan/detail/xiaolongbao_6.json","CategoryName":"午餐","CategoryReName":"wucan"},{"Name":"上汤西洋菜","ImageUrl":"http://site.meishij.net/r/17/180/732517/a732517_142252033232966.jpg","DetailUrl":"http://www.meishij.net/zuofa/shangtangxiyangcai_1.html","DetailID":"wucan/detail/shangtangxiyangcai_1.json","CategoryName":"午餐","CategoryReName":"wucan"},{"Name":"鱼翅排骨鸡肉汤","ImageUrl":"http://site.meishij.net/r/17/180/732517/a732517_142242824625293.jpg","DetailUrl":"http://www.meishij.net/zuofa/yuchipaigujiroutang.html","DetailID":"wucan/detail/yuchipaigujiroutang.json","CategoryName":"午餐","CategoryReName":"wucan"},{"Name":"肉末豆皮卷","ImageUrl":"http://site.meishij.net/r/184/124/2468684/a2468684_142068427132378.jpg","DetailUrl":"http://www.meishij.net/zuofa/roumodoupijuan.html","DetailID":"wucan/detail/roumodoupijuan.json","CategoryName":"午餐","CategoryReName":"wucan"},{"Name":"辣子鸡","ImageUrl":"http://site.meishij.net/r/175/195/3111425/a3111425_142252421509377.jpg","DetailUrl":"http://www.meishij.net/zuofa/jilazi.html","DetailID":"wucan/detail/jilazi.json","CategoryName":"午餐","CategoryReName":"wucan"},{"Name":"速冻豆角炖肉","ImageUrl":"http://site.meishij.net/r/47/191/2860297/a2860297_142252296531364.jpg","DetailUrl":"http://www.meishij.net/zuofa/sudongdoujiaodunrou.html","DetailID":"wucan/detail/sudongdoujiaodunrou.json","CategoryName":"午餐","CategoryReName":"wucan"},{"Name":"上汤菠菜","ImageUrl":"http://site.meishij.net/r/246/137/1534496/a1534496_142251981516303.jpg","DetailUrl":"http://www.meishij.net/zuofa/shangtangbocai_8.html","DetailID":"wucan/detail/shangtangbocai_8.json","CategoryName":"午餐","CategoryReName":"wucan"},{"Name":"猪脆骨焖芋头","ImageUrl":"http://site.meishij.net/r/246/137/1534496/a1534496_142251899303593.jpg","DetailUrl":"http://www.meishij.net/zuofa/zhucuigumenyutou.html","DetailID":"wucan/detail/zhucuigumenyutou.json","CategoryName":"午餐","CategoryReName":"wucan"},{"Name":"腊肠炒芥蓝","ImageUrl":"http://site.meishij.net/r/159/43/1760909/a1760909_142250381999721.jpg","DetailUrl":"http://www.meishij.net/zuofa/lachangchaojielan_2.html","DetailID":"wucan/detail/lachangchaojielan_2.json","CategoryName":"午餐","CategoryReName":"wucan"},{"Name":"清炖羊排","ImageUrl":"http://site.meishij.net/r/112/161/977862/a977862_142251105856728.jpg","DetailUrl":"http://www.meishij.net/zuofa/qingdunyangpai_5.html","DetailID":"wucan/detail/qingdunyangpai_5.json","CategoryName":"午餐","CategoryReName":"wucan"},{"Name":"卤兔腿","ImageUrl":"http://site.meishij.net/r/139/60/2827639/a2827639_142244984583149.jpg","DetailUrl":"http://www.meishij.net/zuofa/lututui_1.html","DetailID":"wucan/detail/lututui_1.json","CategoryName":"午餐","CategoryReName":"wucan"},{"Name":"瑶柱排骨节瓜汤","ImageUrl":"http://site.meishij.net/r/246/137/1534496/a1534496_142245356854637.jpg","DetailUrl":"http://www.meishij.net/zuofa/yaozhupaigujieguatang.html","DetailID":"wucan/detail/yaozhupaigujieguatang.json","CategoryName":"午餐","CategoryReName":"wucan"}]