{"Title":"清蒸羊肉的做法","Primary":["羊腿500克"],"Auxiliary":["食盐适量","葱适量","姜适量","蒜适量","八角适量","料酒适量","浓汤宝适量"],"Flavoring":[],"Setups":["1.羊腿肉洗净切块备用","2.盘子里铺上葱段","[image]:http://images.meishij.net/p/20120222/21834776b81a44535ce2486f37af63c9.jpg","3.放上羊肉块","4.再放上姜片、蒜片、大料，倒上适量料酒","[image]:http://images.meishij.net/p/20120222/7e6812e60cd104016ed463a69c800bca.jpg","5.放入烧开的蒸锅中蒸制15-20分钟","6.将蒸好的羊肉换入汤碗中","[image]:http://images.meishij.net/p/20120222/698ce2f1f6cdf29ae71b5fcdd545a0f9.jpg","7.撒上适量盐","8.放上葱段","9.倒入鸡汤。没有鸡汤就用水代替，我的鸡汤是用浓汤宝清鸡靓汤勾兑的","10.再放入烧开的蒸锅中蒸制15-20分钟即可","[image]:http://images.meishij.net/p/20120222/28f1b04b45a54d44de6319509205271d.jpg","[image]:http://images.meishij.net/p/20120222/5ca63a86306a5e9bd7a44da3e5a589e4.jpg","[image]:http://images.meishij.net/p/20120222/77fba6e6ce153ea534754ee3a2a4dd4d.jpg","烹饪技巧","1、羊肉上的膜最好撕掉，不然会有严重的腥臊味。","2、制作时多放葱姜也可去除膻味，或者放上几颗山楂、萝卜、绿豆也可去膻。","3、可加入胡萝卜或者白萝卜同蒸。","4、最后几分钟放点枸杞再蒸几分钟就更好了，我忘了加。","5、另一种做法是先将羊肉焯水，再入锅蒸30-40分钟，个人觉得这样做更入味一些。","6、羊肉不宜与南瓜、西瓜、鲶鱼同食，也不宜与荞麦、豆瓣酱同食，忌与梅干菜同食。","7、吃羊肉不可加醋，否则内热火攻心。","8、吃完羊肉后不宜马上喝茶，也不宜边吃羊肉边喝茶。"]}