{"Title":"盐烤秋刀鱼的做法","Primary":["秋刀鱼2条"],"Auxiliary":["粗盐10克","柠檬1个","黑胡椒少许","蜂蜜5毫升"],"Flavoring":[],"Setups":["1.秋刀鱼去除内脏鱼腮，洗净沥干，用刀在鱼身上划几刀以便腌制入味；柠檬切半，一半用来挤汁，一半切片备用","2.用粗盐抹在秋刀鱼上，并洒上少许黑胡椒碎粒","[image]:http://images.meishij.net/p/20130902/e966c8c0aecc674c19fd8a06f9e095d1.jpg","3.挤入少许柠檬汁，涂抹均匀后腌30分钟左右，夏天天气热一定要放冰箱低温腌制","4.蜂蜜加适量水搅拌均匀备用","[image]:http://images.meishij.net/p/20130902/54755fed11c08fd8f569e8ece57b3d84.jpg","5.烤箱预热200度，烤盘垫一张锡纸，将腌制好的秋刀鱼放在烤网上，上面放两片柠檬片","6.送入烤箱烘烤10分钟，取出给鱼翻个面，刷上一层蜂蜜水，再继续烘烤10分钟，烤至秋刀鱼表皮金黄微焦即可","[image]:http://images.meishij.net/p/20130902/daf86df5c3197eed82b0bf195057469b.jpg","[image]:http://images.meishij.net/p/20130902/fbdcda631c8617f786b1c167080488a5.jpg","[image]:http://images.meishij.net/p/20130902/ee1dee264817b04a8568a98134ba84b1.jpg","烹饪技巧","　　各家烤箱功力不同，一般是只要看到鱼身微焦、刀口裂开即可，如果没有烤箱，用平底锅小火干煎也是可以的，吃的时候可在秋刀鱼上挤一些新鲜的柠檬汁佐餐。","营养功效","　　秋刀鱼体内含有丰富的蛋白质、脂肪酸，据分析，秋刀鱼含有人体不可缺少的廿碳五烯酸(EPA)、廿二碳六烯酸(DHA)等不饱和脂肪酸，EPA、DHA有抑制高血压、心肌梗塞、动脉硬化的作用。"]}