{"Title":"牌坊面","Primary":[],"Auxiliary":[],"Flavoring":[],"Setups":["                                                                                                                                                                       　　四川简阳县城北门外有一古老面牌坊，周围是集市，人们常在牌坊下的面摊上便餐，而久之称呼为“牌坊面”。原料配方：普通面条500克五花猪肉300克母鸡一只约1250克猪骨头1500克化猪油100克净熟冬笋100克水发青菌(鸡松菌)100白酱油75克食盐25克胡椒粉2.5克老姜100克净大葱150克花椒20粒制作方法：1.锅内加清水，将洗干净的母鸡和猪肉放入水中煮，烧开后捞去浮沫，再将洗净的姜、葱和花椒放入汤锅内同煮，将煮至七成熟的猪肉捞起切成拗甲片，冬笋、青菌也切成指甲片和切好的葱花50克待用；母鸡煮软熟后捞起另作它用；锅内的汤作臊子和煮面条用。2.锅放火上烧热下化猪油，炒切好的猪肉，炒干水分后掺汤，再放入切成指甲片冬笋和青菌、食盐、胡椒面、少量酱油，然后将锅移至小火上慢慢煨靠约半小时，起锅装盆。3.取10个小碗，放入少量酱油、少量鸡汤和切好的葱花。将面条下入开水锅中煮，待面条煮熟浮起时，分别挑入10个小碗内，将臊子浇在面条上即成。产品特点：汤浓味鲜，“臊子”香软化渣。"]}