{"Title":"韭黄蛏子的做法","Primary":["蛏子500克","韭黄200克"],"Auxiliary":["食盐适量","姜适量","料酒少许","植物油适量","鲜贝露5克"],"Flavoring":[],"Setups":["1.蛏子买回来，水里放盐，浸泡半天，洗干净","2.锅内烧开水，放入洗干净的蛏子，烫开口后取出。踢去黑线，取出蛏子肉，冷水洗干净备用","3.韭黄洗干净，切3cm的段，韭黄白，韭黄叶分开","4.开油锅烧热后放入姜丝翻炒后加入蛏子肉翻炒淋入少许料酒至肉收紧后加适量盐","5.先放入韭黄白，炒至变软后加入韭黄叶，根据个人口味加盐（之前放过一些，切记不能放多），淋入5g的鲜贝露，至卤水收干即可","[image]:http://images.meishij.net/p/20120523/8e70290ae67df266f278b612886f0e1c.jpg","[image]:http://images.meishij.net/p/20120523/74596628d83222f3d540d7757021fe15.jpg","烹饪技巧"," 有人说蛏子的处理，要滴几滴油，其实那是错误的，滴油法适合螺蛳的处理，不适合蛏子，这样会把蛏子泡死的哦。"]}