{"Title":"蓝莓蛋挞的做法","Primary":["淡奶油200克","牛奶170克","白糖30克","炼乳30克","鸡蛋黄4个","玉米淀粉6克"],"Auxiliary":["蛋挞皮12克","蓝莓果干适量"],"Flavoring":[],"Setups":["1.把玉米淀粉加入牛奶中搅拌均匀","2.加入糖","3.加入淡奶油","[image]:http://site.meishij.net/rs/114/34/1258614/n1258614_67529.jpg","4.牛奶中加入炼乳和糖","5.小火煮至糖粉等溶化离火，稍微晾凉","6.蛋黄分离出来备用","[image]:http://site.meishij.net/rs/114/34/1258614/n1258614_58767.jpg","7.加入蛋黄，由于奶有点热，边到人边搅拌，搅拌均匀","8.过筛让蛋挞水更细腻","9.备好蓝莓果干","[image]:http://site.meishij.net/rs/114/34/1258614/n1258614_86084.jpg","10.蛋挞水倒入挞皮里，8-9份满的样子，每个里面放入适量的蓝莓干","11.烤箱200度预热5分钟，入烤箱烤15分钟","12.烤好的蛋挞，奶香四溢，还有果干在里面，蛮好吃的哩","[image]:http://site.meishij.net/rs/114/34/1258614/n1258614_16828.jpg","[image]:http://site.meishij.net/rs/114/34/1258614/n1258614_84696.jpg","[image]:http://site.meishij.net/rs/114/34/1258614/n1258614_30173.jpg","[image]:http://site.meishij.net/rs/114/34/1258614/n1258614_83562.jpg","烹饪技巧","蛋挞水一定要过滤一下，这样做出来的蛋挞更细腻香滑。"]}