{"Title":"豉油鸡的做法","Primary":["鸡1000克"],"Auxiliary":["海天酱油适量","姜2小块","蒜头3瓣","糖2茶匙","红米酒2小杯","花生油3汤匙","花生油3汤匙","香葱3根"],"Flavoring":[],"Setups":["1.先把姜削干净切片，再拍蒜头，把葱切段备用","[image]:http://site.meishij.net/rs/26/16/2879026/n2879026_142287707060627.jpg","2.把之前的姜切成姜丝备用","[image]:http://site.meishij.net/rs/26/16/2879026/n2879026_142287714068915.jpg","3.先往鸡身倒进大约半肚酱油用手伸入鸡肚按摩，把酱油抹均匀，再把切好的姜丝，部分葱蒜放进鸡肚中，然后把酱油浇到鸡身上使整个鸡身沾上酱油，腌制30分钟","[image]:http://site.meishij.net/rs/26/16/2879026/n2879026_142287796177818.jpg","4.放3至4汤匙油下锅烧热，放鸡下去不断翻身，炸至金黄然后加入清水、剩余葱段、蒜头，开大火盖锅烧滚","[image]:http://site.meishij.net/rs/26/16/2879026/n2879026_142287867818261.jpg","5.加两茶匙糖，两小杯红米酒，转小火慢焖至干水即可上碟切块","[image]:http://site.meishij.net/rs/26/16/2879026/n2879026_142288166681567.jpg","[image]:http://site.meishij.net/rs/26/16/2879026/n2879026_142288173878470.jpg","烹饪技巧","1、往鸡肚倒进酱油的时候注意把鸡放平，切莫将鸡提起；2、腌制时间保证30分钟左右，颜色味道足够；3、下锅炸鸡时中火为宜，大火容易烧焦。"]}