{"Title":"剁椒鱼头的做法","Primary":["鲢鱼头1个"],"Auxiliary":["食盐1/3小匙","姜1块","料酒1大匙","胡椒粉少许","白酒1大匙","剁椒半碗","蒸鱼豉油1大匙","植物油2大匙","小葱2根"],"Flavoring":[],"Setups":["1.将鱼头洗净，从鱼唇正中剖开，注意不要完全切断，让其连在一起，在鱼头下面鱼肉较厚的部分斜划几刀以方便入味","2.将料酒、胡椒粉、盐撒在鱼头上，抹匀，腌制约20分钟","3.将高度白酒倒入剁椒中，拌匀待用","[image]:http://images.meishij.net/p/20131227/0569f7400a808b62f97d5b87f6254360.jpg","4.在腌制好的鱼头表面淋上少许植物油，抹匀","5.将姜切片，葱切段，铺在碗底","6.再放上处理好的鱼头","[image]:http://images.meishij.net/p/20131227/d5a720e87f4916561fca84c51417c924.jpg","7.然后将步骤3的剁椒铺在鱼头上","8.蒸锅内放入适量的水，烧开，然后摆入鱼头，盖盖，大火隔水足汽蒸约10分钟","9.将蒸好后的鱼头取出，倒去碗内多余的汤汁，撒上葱花，淋入蒸鱼豉油，然后将适量的植物油烧热(表面有少量白烟冒出)，泼在上面即可","[image]:http://images.meishij.net/p/20131227/dd5dfede07481c82547c04071765b342.jpg","[image]:http://images.meishij.net/p/20131227/58f8fa3aa7deaa1be8d415d39c308cab.jpg","[image]:http://images.meishij.net/p/20131227/6756ef93f4b997af46c7455722c1eddb.jpg"]}