{"Title":"剁椒鱼头的做法","Primary":["鲢鱼头1个"],"Auxiliary":["食盐1茶匙","鸡粉1茶匙","姜1块","蒜5瓣","料酒1茶匙","剁椒3汤匙","豆豉1汤匙","小葱2棵","蒸鱼豉油1茶匙","植物油少许"],"Flavoring":[],"Setups":["1.鱼头收拾干净，从鱼唇正中一劈为二背部相连，均匀摸上少量盐、料酒，腌10分钟左右","2.姜、蒜切末，葱切小环状；豆豉泡水稍洗后沥干备用","3.炒锅上火加少量油，爆香姜蒜末加入豆豉炒香后离火","[image]:http://images.meishij.net/p/20130506/09eea90610a7de1aadbea013ff3e538a.jpg","4.将3&mdash;4汤匙太子剁椒拌入其中，再加入少许鸡粉提鲜，全部拌匀","5.盘子底部加少许葱段、姜片，放入鱼头，将拌好的剁椒铺在鱼头表面","6.蒸锅中加水烧开，放入剁椒鱼头，大火蒸制10分钟 ；出锅后撒上香葱末、淋上适量蒸鱼豉油，最后烧1勺热油浇在上面即可","[image]:http://images.meishij.net/p/20130506/5b9b223dfc6911bb497d80f9dc6c72d8.jpg","[image]:http://images.meishij.net/p/20130506/821118181be3c53c81cace9ac9f5ae5a.jpg","[image]:http://images.meishij.net/p/20130506/4e2866d42bd7cd2d5f0978ac686b0f22.jpg","烹饪技巧","1、鱼头的蒸制时间要看材料的大小灵活掌握；","2、剁椒本身已经有咸味，最后又加入了蒸鱼豉油，所以除了开始腌制时的少量盐外，不需要另外加盐了。"]}